kodali/__init__.py
kodali/kodali.py
kodali/named_entity_recognition/__init__.py
kodali/named_entity_recognition/converter.py
kodali/named_entity_recognition/klue.py
kodali/named_entity_recognition/korean_corpus.py
kodali/named_entity_recognition/loader.py
kodali/named_entity_recognition/outputs.py
kodali/named_entity_recognition/scheme.py
kodali/relation_extraction/__init__.py
kodali/relation_extraction/ai_hub.py
kodali/relation_extraction/klue.py
kodali/relation_extraction/loader.py
kodali/relation_extraction/outputs.py
kodali/semantic_role_labeling/__init__.py
kodali/semantic_role_labeling/korean_corpus.py
kodali/semantic_role_labeling/outputs.py
kodali/semantic_role_labeling/scheme.py
kodali/utils/__init__.py
kodali/utils/io.py
kodali-0.3.0.dist-info/METADATA
kodali-0.3.0.dist-info/WHEEL
kodali-0.3.0.dist-info/RECORD
