Metadata-Version: 2.1
Name: kodali
Version: 0.3.0
Summary: Korean Dataset Loading Inferface
Author: Your Name
Author-email: you@example.com
Requires-Python: >=3.8,<4.0
Classifier: Programming Language :: Python :: 3
Classifier: Programming Language :: Python :: 3.8
Classifier: Programming Language :: Python :: 3.9
Classifier: Programming Language :: Python :: 3.10
Classifier: Programming Language :: Python :: 3.11
Requires-Dist: strenum (>=0.4.15,<0.5.0)
Requires-Dist: tqdm (>=4.66.1,<5.0.0)
